wise_client/__init__.py
wise_client/api/__init__.py
wise_client/api/fine_tuning/__init__.py
wise_client/api/fine_tuning/fine_tuning_get_available_models.py
wise_client/api/login/__init__.py
wise_client/api/login/login_get_access_token.py
wise_client/api/media/__init__.py
wise_client/api/media/media_get_file.py
wise_client/api/media/media_get_files.py
wise_client/api/projects/__init__.py
wise_client/api/projects/projects_get_lisa_schema.py
wise_client/api/projects/projects_get_projects_me.py
wise_client/api/projects/projects_projectscreate_project.py
wise_client/api/projects/projects_projectsdelete_project.py
wise_client/api/projects/projects_projectsget_project.py
wise_client/api/projects/projects_projectsupload_documents.py
wise_client/client.py
wise_client/errors.py
wise_client/models/__init__.py
wise_client/models/available_models.py
wise_client/models/base_project_schema.py
wise_client/models/body_login_get_access_token.py
wise_client/models/body_projects_projectsupload_documents.py
wise_client/models/completion_schema.py
wise_client/models/consumption_tier.py
wise_client/models/history_value.py
wise_client/models/http_validation_error.py
wise_client/models/lisa_schema.py
wise_client/models/project_document_schema.py
wise_client/models/project_document_status.py
wise_client/models/project_schema.py
wise_client/models/validation_error.py
wise_client/models/values.py
wise_client/py.typed
wise_client/types.py
sunwise_wise_client-0.1.2.dist-info/METADATA
sunwise_wise_client-0.1.2.dist-info/WHEEL
sunwise_wise_client-0.1.2.dist-info/RECORD
